{
    "questions": [
      {"heading": "Was Weißt du Über Nador?"},
      {
        "question": "Wann war Marokko unabhängig?",
        "translation": "When did Morocco gain independence?",
        "options": [
          {
            "value": "a",
            "id": "a",
            "label": "1951"
          },
          {
            "value": "b",
            "id": "b",
            "label": "1956"
          },
          {
            "value": "c",
            "id": "c",
            "label": "1961"
          },
          {
            "value": "d",
            "id": "d",
            "label": "1969"
          }
        ]
      },
      {
        "question": "Einer wichtigsten Exporte von Nador ist...",
        "translation": "A significant export of Nador's is...",
        "options": [
          {
            "value": "a",
            "id": "a",
            "label": "Fisch"
          },
          {
            "value": "b",
            "id": "b",
            "label": "Tofu"
          },
          {
            "value": "c",
            "id": "c",
            "label": "Gartenzwerge"
          },
          {
            "value": "d",
            "id": "d",
            "label": "Stahl"
          }
        ]
      },
      {
        "question": "",
        "translation": "",
        "options": [
          {
            "value": "a",
            "id": "a",
            "label": ""
          },
          {
            "value": "b",
            "id": "b",
            "label": ""
          },
          {
            "value": "c",
            "id": "c",
            "label": ""
          },
          {
            "value": "d",
            "id": "d",
            "label": ""
          }
        ]
      },
      {"heading": "Kennst Du Hanan?"},
      {
        "question": "",
        "translation": "",
        "options": [
          {
            "value": "a",
            "id": "a",
            "label": ""
          },
          {
            "value": "b",
            "id": "b",
            "label": ""
          },
          {
            "value": "c",
            "id": "c",
            "label": ""
          },
          {
            "value": "d",
            "id": "d",
            "label": ""
          }
        ]
      },
      {
        "question": "",
        "translation": "",
        "options": [
          {
            "value": "a",
            "id": "a",
            "label": ""
          },
          {
            "value": "b",
            "id": "b",
            "label": ""
          },
          {
            "value": "c",
            "id": "c",
            "label": ""
          },
          {
            "value": "d",
            "id": "d",
            "label": ""
          }
        ]
      },
      {
        "question": "",
        "translation": "",
        "options": [
          {
            "value": "a",
            "id": "a",
            "label": ""
          },
          {
            "value": "b",
            "id": "b",
            "label": ""
          },
          {
            "value": "c",
            "id": "c",
            "label": ""
          },
          {
            "value": "d",
            "id": "d",
            "label": ""
          }
        ]
      }
    ],
    "answers": ["b", "a", "c", "", "", ""]
  }
